fairospy/__init__.py
fairospy/fair_doc_db.py
fairospy/fair_fs.py
fairospy/fair_kv.py
fairospy/core/__init__.py
fairospy/core/base_obj.py
fairospy/core/fair_os.py
fairospy/core/fair_pod.py
fairospy/core/fair_user.py
fairos_py_sdk-0.0.2.dist-info/LICENSE
fairos_py_sdk-0.0.2.dist-info/METADATA
fairos_py_sdk-0.0.2.dist-info/WHEEL
fairos_py_sdk-0.0.2.dist-info/top_level.txt
fairos_py_sdk-0.0.2.dist-info/RECORD
